flashtext/__init__.py
flashtext/keyword.py
flashtext-mod/__init__.py
flashtext-mod/keyword.py
flashtext_mod-2.77.dist-info/LICENSE
flashtext_mod-2.77.dist-info/METADATA
flashtext_mod-2.77.dist-info/WHEEL
flashtext_mod-2.77.dist-info/top_level.txt
flashtext_mod-2.77.dist-info/RECORD
