Metadata-Version: 2.1
Name: flashtext-mod
Version: 2.77
Summary: Extract/Replaces keywords in sentences.
Home-page: https://github.com/brlala/flashtext-mod
Author: brlala
Author-email: henrytlh@hotmail.com
License: UNKNOWN
Platform: any
Classifier: Programming Language :: Python
Classifier: Programming Language :: Python :: 2.7
Classifier: Programming Language :: Python :: 3.5
Classifier: Programming Language :: Python :: 3.6
Classifier: Operating System :: OS Independent
Classifier: Intended Audience :: Developers
Classifier: License :: OSI Approved :: MIT License
